py3simplesoap/__init__.py
py3simplesoap/client.py
py3simplesoap/server.py
py3simplesoap/simplexml.py
py3simplesoap/transport.py
py3simplesoap-0.10.18.dist-info/METADATA
py3simplesoap-0.10.18.dist-info/WHEEL
py3simplesoap-0.10.18.dist-info/top_level.txt
py3simplesoap-0.10.18.dist-info/RECORD
