Metadata-Version: 2.1
Name: py3simplesoap
Version: 0.10.18
Summary: py3simplesoap for python3
Home-page: https://github.com/odoo-mastercore/py3simplesoap
Author: Mastercore
Author-email: far@mastercore.net
License: UNKNOWN
Download-URL: https://github.com/odoo-mastercore/py3simplesoap/tarball/0.1
Keywords: py3simplesoap,py3
Platform: UNKNOWN
Classifier: Development Status :: 4 - Beta
Classifier: Intended Audience :: Developers
Classifier: Topic :: Software Development :: Build Tools
Classifier: Programming Language :: Python :: 3
Classifier: Programming Language :: Python :: 3.2
Classifier: Programming Language :: Python :: 3.3
Classifier: Programming Language :: Python :: 3.4
